[{"source": {"type": "file", "filename": "captured_image_1719082270.jpg", "content_type": "image/jpeg", "md5sum": "4079c9e57a9931fac62ac5eba04e5c7d"}, "results": {"predictions": [{"file": "captured_image_1719082270.jpg", "file_type": "image", "models": {"face": {"metadata": null, "grouped_predictions": [{"id": "unknown", "predictions": [{"frame": 0, "time": 0.0, "prob": 0.9999996423721313, "box": {"x": 232.21517944335938, "y": 157.09039306640625, "w": 178.50042724609375, "h": 253.9342041015625}, "emotions": [{"name": "Admiration", "score": 0.0597318559885025}, {"name": "Adoration", "score": 0.03324240818619728}, {"name": "Aesthetic Appreciation", "score": 0.05199265107512474}, {"name": "Amusement", "score": 0.050521668046712875}, {"name": "Anger", "score": 0.18302921950817108}, {"name": "Anxiety", "score": 0.18062183260917664}, {"name": "Awe", "score": 0.06781291961669922}, {"name": "Awkwardness", "score": 0.195923313498497}, {"name": "Boredom", "score": 0.5014825463294983}, {"name": "Calmness", "score": 0.4621430039405823}, {"name": "Concentration", "score": 0.5755378603935242}, {"name": "Confusion", "score": 0.4201262593269348}, {"name": "Contemplation", "score": 0.251749187707901}, {"name": "Contempt", "score": 0.2675119936466217}, {"name": "Contentment", "score": 0.07762785255908966}, {"name": "Craving", "score": 0.04845890402793884}, {"name": "Desire", "score": 0.030714988708496094}, {"name": "Determination", "score": 0.20066669583320618}, {"name": "Disappointment", "score": 0.38567665219306946}, {"name": "Disgust", "score": 0.127399280667305}, {"name": "Distress", "score": 0.1970333307981491}, {"name": "Doubt", "score": 0.3975584805011749}, {"name": "Ecstasy", "score": 0.013373332098126411}, {"name": "Embarrassment", "score": 0.08574716746807098}, {"name": "Empathic Pain", "score": 0.08836027979850769}, {"name": "Entrancement", "score": 0.11994055658578873}, {"name": "Envy", "score": 0.06581414490938187}, {"name": "Excitement", "score": 0.023913519456982613}, {"name": "Fear", "score": 0.09890773892402649}, {"name": "Guilt", "score": 0.09200197458267212}, {"name": "Horror", "score": 0.03793174400925636}, {"name": "Interest", "score": 0.2374454140663147}, {"name": "Joy", "score": 0.024829622358083725}, {"name": "Love", "score": 0.032197315245866776}, {"name": "Nostalgia", "score": 0.058712512254714966}, {"name": "Pain", "score": 0.09743903577327728}, {"name": "Pride", "score": 0.05746915936470032}, {"name": "Realization", "score": 0.13895930349826813}, {"name": "Relief", "score": 0.03609384968876839}, {"name": "Romance", "score": 0.021371055394411087}, {"name": "Sadness", "score": 0.26566097140312195}, {"name": "Satisfaction", "score": 0.05017319321632385}, {"name": "Shame", "score": 0.07353053241968155}, {"name": "Surprise (negative)", "score": 0.05233416706323624}, {"name": "Surprise (positive)", "score": 0.028767377138137817}, {"name": "Sympathy", "score": 0.05815359205007553}, {"name": "Tiredness", "score": 0.24405257403850555}, {"name": "Triumph", "score": 0.019466251134872437}], "facs": null, "descriptions": null}]}]}}}], "errors": []}}]