[{"source": {"type": "file", "filename": "captured_image_1719080166.jpg", "content_type": "image/jpeg", "md5sum": "9b92445ce303dbc3514fe14103103016"}, "results": {"predictions": [{"file": "captured_image_1719080166.jpg", "file_type": "image", "models": {"face": {"metadata": null, "grouped_predictions": [{"id": "unknown", "predictions": [{"frame": 0, "time": 0.0, "prob": 0.9999990463256836, "box": {"x": 282.13226318359375, "y": 123.02423095703125, "w": 186.99093627929688, "h": 239.61907958984375}, "emotions": [{"name": "Admiration", "score": 0.0812864676117897}, {"name": "Adoration", "score": 0.04617692902684212}, {"name": "Aesthetic Appreciation", "score": 0.05645338445901871}, {"name": "Amusement", "score": 0.10012805461883545}, {"name": "Anger", "score": 0.056979697197675705}, {"name": "Anxiety", "score": 0.2511027455329895}, {"name": "Awe", "score": 0.16547024250030518}, {"name": "Awkwardness", "score": 0.20246951282024384}, {"name": "Boredom", "score": 0.30630311369895935}, {"name": "Calmness", "score": 0.2936188578605652}, {"name": "Concentration", "score": 0.6275282502174377}, {"name": "Confusion", "score": 0.47198769450187683}, {"name": "Contemplation", "score": 0.33327946066856384}, {"name": "Contempt", "score": 0.0923478752374649}, {"name": "Contentment", "score": 0.06397312879562378}, {"name": "Craving", "score": 0.07374963909387589}, {"name": "Desire", "score": 0.06303785741329193}, {"name": "Determination", "score": 0.1426835060119629}, {"name": "Disappointment", "score": 0.23963120579719543}, {"name": "Disgust", "score": 0.0551791787147522}, {"name": "Distress", "score": 0.21806053817272186}, {"name": "Doubt", "score": 0.40889766812324524}, {"name": "Ecstasy", "score": 0.02511034719645977}, {"name": "Embarrassment", "score": 0.11421933025121689}, {"name": "Empathic Pain", "score": 0.07932967692613602}, {"name": "Entrancement", "score": 0.1523684859275818}, {"name": "Envy", "score": 0.041921548545360565}, {"name": "Excitement", "score": 0.06258255243301392}, {"name": "Fear", "score": 0.21398647129535675}, {"name": "Guilt", "score": 0.11294179409742355}, {"name": "Horror", "score": 0.1088196337223053}, {"name": "Interest", "score": 0.3351394832134247}, {"name": "Joy", "score": 0.0436282679438591}, {"name": "Love", "score": 0.047466009855270386}, {"name": "Nostalgia", "score": 0.05195392668247223}, {"name": "Pain", "score": 0.07840471714735031}, {"name": "Pride", "score": 0.032082945108413696}, {"name": "Realization", "score": 0.21799200773239136}, {"name": "Relief", "score": 0.03384597972035408}, {"name": "Romance", "score": 0.03566627576947212}, {"name": "Sadness", "score": 0.1730000078678131}, {"name": "Satisfaction", "score": 0.05609014630317688}, {"name": "Shame", "score": 0.07499239593744278}, {"name": "Surprise (negative)", "score": 0.14832662045955658}, {"name": "Surprise (positive)", "score": 0.12235002964735031}, {"name": "Sympathy", "score": 0.06158387288451195}, {"name": "Tiredness", "score": 0.15768109261989594}, {"name": "Triumph", "score": 0.017254918813705444}], "facs": null, "descriptions": null}]}]}}}], "errors": []}}]