[{"source": {"type": "file", "filename": "captured_image_1719080171.jpg", "content_type": "image/jpeg", "md5sum": "5e3fb45ba5c4fdce13dd8d604676a61d"}, "results": {"predictions": [{"file": "captured_image_1719080171.jpg", "file_type": "image", "models": {"face": {"metadata": null, "grouped_predictions": [{"id": "unknown", "predictions": [{"frame": 0, "time": 0.0, "prob": 0.9999991655349731, "box": {"x": 278.58343505859375, "y": 129.13522338867188, "w": 185.86868286132812, "h": 232.34588623046875}, "emotions": [{"name": "Admiration", "score": 0.07112426310777664}, {"name": "Adoration", "score": 0.04421921446919441}, {"name": "Aesthetic Appreciation", "score": 0.055427201092243195}, {"name": "Amusement", "score": 0.08709104359149933}, {"name": "Anger", "score": 0.05310536175966263}, {"name": "Anxiety", "score": 0.2490679770708084}, {"name": "Awe", "score": 0.09735266864299774}, {"name": "Awkwardness", "score": 0.17517417669296265}, {"name": "Boredom", "score": 0.3298918306827545}, {"name": "Calmness", "score": 0.32865598797798157}, {"name": "Concentration", "score": 0.7092688679695129}, {"name": "Confusion", "score": 0.4628118872642517}, {"name": "Contemplation", "score": 0.409294068813324}, {"name": "Contempt", "score": 0.09401337802410126}, {"name": "Contentment", "score": 0.06921593844890594}, {"name": "Craving", "score": 0.07021450251340866}, {"name": "Desire", "score": 0.0654236301779747}, {"name": "Determination", "score": 0.1500542163848877}, {"name": "Disappointment", "score": 0.25507521629333496}, {"name": "Disgust", "score": 0.05497535318136215}, {"name": "Distress", "score": 0.2336919903755188}, {"name": "Doubt", "score": 0.41310590505599976}, {"name": "Ecstasy", "score": 0.021974647417664528}, {"name": "Embarrassment", "score": 0.09880045056343079}, {"name": "Empathic Pain", "score": 0.08795439451932907}, {"name": "Entrancement", "score": 0.14317724108695984}, {"name": "Envy", "score": 0.03953609988093376}, {"name": "Excitement", "score": 0.04709374159574509}, {"name": "Fear", "score": 0.15249580144882202}, {"name": "Guilt", "score": 0.12098477780818939}, {"name": "Horror", "score": 0.06135562062263489}, {"name": "Interest", "score": 0.3282596468925476}, {"name": "Joy", "score": 0.04328617453575134}, {"name": "Love", "score": 0.04939787834882736}, {"name": "Nostalgia", "score": 0.05759159103035927}, {"name": "Pain", "score": 0.09866534173488617}, {"name": "Pride", "score": 0.03273449465632439}, {"name": "Realization", "score": 0.19115862250328064}, {"name": "Relief", "score": 0.0348566398024559}, {"name": "Romance", "score": 0.03698468580842018}, {"name": "Sadness", "score": 0.23181316256523132}, {"name": "Satisfaction", "score": 0.0594681017100811}, {"name": "Shame", "score": 0.08047708868980408}, {"name": "Surprise (negative)", "score": 0.0792812630534172}, {"name": "Surprise (positive)", "score": 0.05836028233170509}, {"name": "Sympathy", "score": 0.06800216436386108}, {"name": "Tiredness", "score": 0.18367114663124084}, {"name": "Triumph", "score": 0.015294062905013561}], "facs": null, "descriptions": null}]}]}}}], "errors": []}}]