[{"source": {"type": "file", "filename": "captured_image_1719081674.jpg", "content_type": "image/jpeg", "md5sum": "116f373daa6353a7172f51076b85c7e8"}, "results": {"predictions": [{"file": "captured_image_1719081674.jpg", "file_type": "image", "models": {"face": {"metadata": null, "grouped_predictions": [{"id": "unknown", "predictions": [{"frame": 0, "time": 0.0, "prob": 1.0, "box": {"x": 239.07122802734375, "y": 151.77899169921875, "w": 158.3743896484375, "h": 206.43954467773438}, "emotions": [{"name": "Admiration", "score": 0.07562887668609619}, {"name": "Adoration", "score": 0.047837309539318085}, {"name": "Aesthetic Appreciation", "score": 0.05820596590638161}, {"name": "Amusement", "score": 0.1117483451962471}, {"name": "Anger", "score": 0.0972750261425972}, {"name": "Anxiety", "score": 0.1697923243045807}, {"name": "Awe", "score": 0.12661665678024292}, {"name": "Awkwardness", "score": 0.2775956988334656}, {"name": "Boredom", "score": 0.349037230014801}, {"name": "Calmness", "score": 0.34223219752311707}, {"name": "Concentration", "score": 0.4304567873477936}, {"name": "Confusion", "score": 0.6047958731651306}, {"name": "Contemplation", "score": 0.17871569097042084}, {"name": "Contempt", "score": 0.21925601363182068}, {"name": "Contentment", "score": 0.08279818296432495}, {"name": "Craving", "score": 0.07135163247585297}, {"name": "Desire", "score": 0.08595729619264603}, {"name": "Determination", "score": 0.11911269277334213}, {"name": "Disappointment", "score": 0.2684662640094757}, {"name": "Disgust", "score": 0.1732485443353653}, {"name": "Distress", "score": 0.19304397702217102}, {"name": "Doubt", "score": 0.38386160135269165}, {"name": "Ecstasy", "score": 0.028545500710606575}, {"name": "Embarrassment", "score": 0.09911327809095383}, {"name": "Empathic Pain", "score": 0.07890143245458603}, {"name": "Entrancement", "score": 0.12781822681427002}, {"name": "Envy", "score": 0.05201549828052521}, {"name": "Excitement", "score": 0.06177946552634239}, {"name": "Fear", "score": 0.13651682436466217}, {"name": "Guilt", "score": 0.06826484203338623}, {"name": "Horror", "score": 0.07733135670423508}, {"name": "Interest", "score": 0.29436224699020386}, {"name": "Joy", "score": 0.05918540433049202}, {"name": "Love", "score": 0.05398029834032059}, {"name": "Nostalgia", "score": 0.0474776029586792}, {"name": "Pain", "score": 0.09585754573345184}, {"name": "Pride", "score": 0.04321806877851486}, {"name": "Realization", "score": 0.16457247734069824}, {"name": "Relief", "score": 0.050114620476961136}, {"name": "Romance", "score": 0.03580182045698166}, {"name": "Sadness", "score": 0.14703118801116943}, {"name": "Satisfaction", "score": 0.08139488101005554}, {"name": "Shame", "score": 0.06049540266394615}, {"name": "Surprise (negative)", "score": 0.12080662697553635}, {"name": "Surprise (positive)", "score": 0.07261292636394501}, {"name": "Sympathy", "score": 0.053305741399526596}, {"name": "Tiredness", "score": 0.1952989101409912}, {"name": "Triumph", "score": 0.023732081055641174}], "facs": null, "descriptions": null}]}]}}}], "errors": []}}]