[{"source": {"type": "file", "filename": "captured_image_1719082019.jpg", "content_type": "image/jpeg", "md5sum": "e5ed5bfdee2e07ac65adf147b38b7800"}, "results": {"predictions": [{"file": "captured_image_1719082019.jpg", "file_type": "image", "models": {"face": {"metadata": null, "grouped_predictions": [{"id": "unknown", "predictions": [{"frame": 0, "time": 0.0, "prob": 0.9999997615814209, "box": {"x": 232.71498107910156, "y": 173.89920043945312, "w": 161.6073760986328, "h": 205.78878784179688}, "emotions": [{"name": "Admiration", "score": 0.05900223180651665}, {"name": "Adoration", "score": 0.037633270025253296}, {"name": "Aesthetic Appreciation", "score": 0.04527449980378151}, {"name": "Amusement", "score": 0.060899753123521805}, {"name": "Anger", "score": 0.03966481238603592}, {"name": "Anxiety", "score": 0.3290199637413025}, {"name": "Awe", "score": 0.07524518668651581}, {"name": "Awkwardness", "score": 0.13397572934627533}, {"name": "Boredom", "score": 0.2578536868095398}, {"name": "Calmness", "score": 0.25595223903656006}, {"name": "Concentration", "score": 0.7234535217285156}, {"name": "Confusion", "score": 0.4817965626716614}, {"name": "Contemplation", "score": 0.5483190417289734}, {"name": "Contempt", "score": 0.07171110063791275}, {"name": "Contentment", "score": 0.05248288810253143}, {"name": "Craving", "score": 0.050689321011304855}, {"name": "Desire", "score": 0.0430414155125618}, {"name": "Determination", "score": 0.12514916062355042}, {"name": "Disappointment", "score": 0.2777111530303955}, {"name": "Disgust", "score": 0.045968569815158844}, {"name": "Distress", "score": 0.32378169894218445}, {"name": "Doubt", "score": 0.4509357213973999}, {"name": "Ecstasy", "score": 0.01615883596241474}, {"name": "Embarrassment", "score": 0.10472844541072845}, {"name": "Empathic Pain", "score": 0.1063147783279419}, {"name": "Entrancement", "score": 0.12531566619873047}, {"name": "Envy", "score": 0.03138592839241028}, {"name": "Excitement", "score": 0.03175845369696617}, {"name": "Fear", "score": 0.17800438404083252}, {"name": "Guilt", "score": 0.16419431567192078}, {"name": "Horror", "score": 0.05687243863940239}, {"name": "Interest", "score": 0.26806727051734924}, {"name": "Joy", "score": 0.03129812330007553}, {"name": "Love", "score": 0.04130281135439873}, {"name": "Nostalgia", "score": 0.06297587603330612}, {"name": "Pain", "score": 0.13464830815792084}, {"name": "Pride", "score": 0.024393565952777863}, {"name": "Realization", "score": 0.20777396857738495}, {"name": "Relief", "score": 0.030485643073916435}, {"name": "Romance", "score": 0.03156420961022377}, {"name": "Sadness", "score": 0.32095474004745483}, {"name": "Satisfaction", "score": 0.04255802929401398}, {"name": "Shame", "score": 0.1003451719880104}, {"name": "Surprise (negative)", "score": 0.06365299224853516}, {"name": "Surprise (positive)", "score": 0.03828030452132225}, {"name": "Sympathy", "score": 0.07184340804815292}, {"name": "Tiredness", "score": 0.18272927403450012}, {"name": "Triumph", "score": 0.010544795542955399}], "facs": null, "descriptions": null}]}]}}}], "errors": []}}]