[{"source": {"type": "file", "filename": "captured_image_1719083099.jpg", "content_type": "image/jpeg", "md5sum": "453daf2b40381d7888cfbf6a1f2829c6"}, "results": {"predictions": [{"file": "captured_image_1719083099.jpg", "file_type": "image", "models": {"face": {"metadata": null, "grouped_predictions": [{"id": "unknown", "predictions": [{"frame": 0, "time": 0.0, "prob": 0.9992290735244751, "box": {"x": -194.4664306640625, "y": 137.66793823242188, "w": 294.26231384277344, "h": 314.0613708496094}, "emotions": [{"name": "Admiration", "score": 0.09018822759389877}, {"name": "Adoration", "score": 0.08713775873184204}, {"name": "Aesthetic Appreciation", "score": 0.048687420785427094}, {"name": "Amusement", "score": 0.22551827132701874}, {"name": "Anger", "score": 0.0734260082244873}, {"name": "Anxiety", "score": 0.24977174401283264}, {"name": "Awe", "score": 0.126048281788826}, {"name": "Awkwardness", "score": 0.2075759917497635}, {"name": "Boredom", "score": 0.20216591656208038}, {"name": "Calmness", "score": 0.1929284632205963}, {"name": "Concentration", "score": 0.2539176642894745}, {"name": "Confusion", "score": 0.3405246436595917}, {"name": "Contemplation", "score": 0.18005651235580444}, {"name": "Contempt", "score": 0.09265422075986862}, {"name": "Contentment", "score": 0.10466649383306503}, {"name": "Craving", "score": 0.04036644846200943}, {"name": "Desire", "score": 0.04502513259649277}, {"name": "Determination", "score": 0.07597638666629791}, {"name": "Disappointment", "score": 0.40380972623825073}, {"name": "Disgust", "score": 0.09497755765914917}, {"name": "Distress", "score": 0.38843175768852234}, {"name": "Doubt", "score": 0.2602494955062866}, {"name": "Ecstasy", "score": 0.058902427554130554}, {"name": "Embarrassment", "score": 0.23908273875713348}, {"name": "Empathic Pain", "score": 0.15240313112735748}, {"name": "Entrancement", "score": 0.08833988010883331}, {"name": "Envy", "score": 0.030952978879213333}, {"name": "Excitement", "score": 0.12349970638751984}, {"name": "Fear", "score": 0.16844244301319122}, {"name": "Guilt", "score": 0.16471298038959503}, {"name": "Horror", "score": 0.09671448171138763}, {"name": "Interest", "score": 0.19588015973567963}, {"name": "Joy", "score": 0.16108715534210205}, {"name": "Love", "score": 0.12901951372623444}, {"name": "Nostalgia", "score": 0.07081450521945953}, {"name": "Pain", "score": 0.3072621524333954}, {"name": "Pride", "score": 0.058619074523448944}, {"name": "Realization", "score": 0.2246915102005005}, {"name": "Relief", "score": 0.11292073875665665}, {"name": "Romance", "score": 0.05342502146959305}, {"name": "Sadness", "score": 0.38123321533203125}, {"name": "Satisfaction", "score": 0.12984248995780945}, {"name": "Shame", "score": 0.15871310234069824}, {"name": "Surprise (negative)", "score": 0.104810930788517}, {"name": "Surprise (positive)", "score": 0.08612952381372452}, {"name": "Sympathy", "score": 0.07499180734157562}, {"name": "Tiredness", "score": 0.2712245583534241}, {"name": "Triumph", "score": 0.04122959449887276}], "facs": null, "descriptions": null}, {"frame": 0, "time": 0.0, "prob": 0.9999957084655762, "box": {"x": 429.2994079589844, "y": 208.02354431152344, "w": 113.27572631835938, "h": 154.9679412841797}, "emotions": [{"name": "Admiration", "score": 0.12462849915027618}, {"name": "Adoration", "score": 0.09594599902629852}, {"name": "Aesthetic Appreciation", "score": 0.08023843914270401}, {"name": "Amusement", "score": 0.17848552763462067}, {"name": "Anger", "score": 0.0620320625603199}, {"name": "Anxiety", "score": 0.15053199231624603}, {"name": "Awe", "score": 0.11752138286828995}, {"name": "Awkwardness", "score": 0.25103968381881714}, {"name": "Boredom", "score": 0.34940221905708313}, {"name": "Calmness", "score": 0.45944175124168396}, {"name": "Concentration", "score": 0.45976436138153076}, {"name": "Confusion", "score": 0.5346940755844116}, {"name": "Contemplation", "score": 0.21396669745445251}, {"name": "Contempt", "score": 0.18002407252788544}, {"name": "Contentment", "score": 0.15023024380207062}, {"name": "Craving", "score": 0.059506747871637344}, {"name": "Desire", "score": 0.07928553223609924}, {"name": "Determination", "score": 0.11105946451425552}, {"name": "Disappointment", "score": 0.23749865591526031}, {"name": "Disgust", "score": 0.10045585036277771}, {"name": "Distress", "score": 0.1659516543149948}, {"name": "Doubt", "score": 0.3672342300415039}, {"name": "Ecstasy", "score": 0.03743085265159607}, {"name": "Embarrassment", "score": 0.09491670876741409}, {"name": "Empathic Pain", "score": 0.06902903318405151}, {"name": "Entrancement", "score": 0.14378997683525085}, {"name": "Envy", "score": 0.050250597298145294}, {"name": "Excitement", "score": 0.09059775620698929}, {"name": "Fear", "score": 0.1054837703704834}, {"name": "Guilt", "score": 0.06563010811805725}, {"name": "Horror", "score": 0.05161358788609505}, {"name": "Interest", "score": 0.3994605243206024}, {"name": "Joy", "score": 0.13668882846832275}, {"name": "Love", "score": 0.1198282539844513}, {"name": "Nostalgia", "score": 0.06530854105949402}, {"name": "Pain", "score": 0.0798543393611908}, {"name": "Pride", "score": 0.06259047985076904}, {"name": "Realization", "score": 0.1690969616174698}, {"name": "Relief", "score": 0.07588627934455872}, {"name": "Romance", "score": 0.05592397600412369}, {"name": "Sadness", "score": 0.13770528137683868}, {"name": "Satisfaction", "score": 0.14150284230709076}, {"name": "Shame", "score": 0.057824745774269104}, {"name": "Surprise (negative)", "score": 0.0787903442978859}, {"name": "Surprise (positive)", "score": 0.06634853035211563}, {"name": "Sympathy", "score": 0.06982610374689102}, {"name": "Tiredness", "score": 0.19465988874435425}, {"name": "Triumph", "score": 0.030043216422200203}], "facs": null, "descriptions": null}]}]}}}], "errors": []}}]