[{"source": {"type": "file", "filename": "captured_image_1719079871.jpg", "content_type": "image/jpeg", "md5sum": "43bd816620266b5b4d7e50759b5cc34c"}, "results": {"predictions": [{"file": "captured_image_1719079871.jpg", "file_type": "image", "models": {"face": {"metadata": null, "grouped_predictions": [{"id": "unknown", "predictions": [{"frame": 0, "time": 0.0, "prob": 1.0, "box": {"x": 218.18067932128906, "y": 99.76667785644531, "w": 186.7454071044922, "h": 244.6958465576172}, "emotions": [{"name": "Admiration", "score": 0.062236957252025604}, {"name": "Adoration", "score": 0.03630957752466202}, {"name": "Aesthetic Appreciation", "score": 0.048126332461833954}, {"name": "Amusement", "score": 0.06799430400133133}, {"name": "Anger", "score": 0.12158190459012985}, {"name": "Anxiety", "score": 0.1938336342573166}, {"name": "Awe", "score": 0.11717475950717926}, {"name": "Awkwardness", "score": 0.2506587505340576}, {"name": "Boredom", "score": 0.2974034249782562}, {"name": "Calmness", "score": 0.25308820605278015}, {"name": "Concentration", "score": 0.3816015124320984}, {"name": "Confusion", "score": 0.7092908620834351}, {"name": "Contemplation", "score": 0.19905400276184082}, {"name": "Contempt", "score": 0.25826188921928406}, {"name": "Contentment", "score": 0.058005038648843765}, {"name": "Craving", "score": 0.051827769726514816}, {"name": "Desire", "score": 0.04327546805143356}, {"name": "Determination", "score": 0.11242910474538803}, {"name": "Disappointment", "score": 0.3256397843360901}, {"name": "Disgust", "score": 0.21585440635681152}, {"name": "Distress", "score": 0.24260951578617096}, {"name": "Doubt", "score": 0.46168816089630127}, {"name": "Ecstasy", "score": 0.018504731357097626}, {"name": "Embarrassment", "score": 0.10463102161884308}, {"name": "Empathic Pain", "score": 0.09748261421918869}, {"name": "Entrancement", "score": 0.10720115900039673}, {"name": "Envy", "score": 0.05574797838926315}, {"name": "Excitement", "score": 0.036488067358732224}, {"name": "Fear", "score": 0.15938107669353485}, {"name": "Guilt", "score": 0.07892550528049469}, {"name": "Horror", "score": 0.0849524587392807}, {"name": "Interest", "score": 0.21926632523536682}, {"name": "Joy", "score": 0.03210410103201866}, {"name": "Love", "score": 0.03345642611384392}, {"name": "Nostalgia", "score": 0.05039706826210022}, {"name": "Pain", "score": 0.1272391825914383}, {"name": "Pride", "score": 0.03986535966396332}, {"name": "Realization", "score": 0.16844816505908966}, {"name": "Relief", "score": 0.03933798521757126}, {"name": "Romance", "score": 0.022659199312329292}, {"name": "Sadness", "score": 0.19736459851264954}, {"name": "Satisfaction", "score": 0.05034498870372772}, {"name": "Shame", "score": 0.06885771453380585}, {"name": "Surprise (negative)", "score": 0.11332172900438309}, {"name": "Surprise (positive)", "score": 0.05120425671339035}, {"name": "Sympathy", "score": 0.0544605553150177}, {"name": "Tiredness", "score": 0.18213807046413422}, {"name": "Triumph", "score": 0.01940697245299816}], "facs": null, "descriptions": null}]}]}}}], "errors": []}}]