[{"source": {"type": "file", "filename": "captured_image_1719082964.jpg", "content_type": "image/jpeg", "md5sum": "4b620f2656347b9576a1d19f0a5946ab"}, "results": {"predictions": [{"file": "captured_image_1719082964.jpg", "file_type": "image", "models": {"face": {"metadata": null, "grouped_predictions": [{"id": "unknown", "predictions": [{"frame": 0, "time": 0.0, "prob": 0.9999984502792358, "box": {"x": 264.394775390625, "y": 180.53652954101562, "w": 154.14834594726562, "h": 197.12997436523438}, "emotions": [{"name": "Admiration", "score": 0.07749764621257782}, {"name": "Adoration", "score": 0.04644958674907684}, {"name": "Aesthetic Appreciation", "score": 0.05665788799524307}, {"name": "Amusement", "score": 0.08502092212438583}, {"name": "Anger", "score": 0.04229752719402313}, {"name": "Anxiety", "score": 0.2799704074859619}, {"name": "Awe", "score": 0.12022791057825089}, {"name": "Awkwardness", "score": 0.16806656122207642}, {"name": "Boredom", "score": 0.31273913383483887}, {"name": "Calmness", "score": 0.31065496802330017}, {"name": "Concentration", "score": 0.7206328511238098}, {"name": "Confusion", "score": 0.498712420463562}, {"name": "Contemplation", "score": 0.4440893828868866}, {"name": "Contempt", "score": 0.08195602148771286}, {"name": "Contentment", "score": 0.0639287531375885}, {"name": "Craving", "score": 0.07060230523347855}, {"name": "Desire", "score": 0.06888943910598755}, {"name": "Determination", "score": 0.13673025369644165}, {"name": "Disappointment", "score": 0.22858422994613647}, {"name": "Disgust", "score": 0.04750318452715874}, {"name": "Distress", "score": 0.24221283197402954}, {"name": "Doubt", "score": 0.4370482265949249}, {"name": "Ecstasy", "score": 0.02186092548072338}, {"name": "Embarrassment", "score": 0.09645532071590424}, {"name": "Empathic Pain", "score": 0.08234129846096039}, {"name": "Entrancement", "score": 0.15604327619075775}, {"name": "Envy", "score": 0.037647146731615067}, {"name": "Excitement", "score": 0.048859935253858566}, {"name": "Fear", "score": 0.19430449604988098}, {"name": "Guilt", "score": 0.11823251843452454}, {"name": "Horror", "score": 0.07853368669748306}, {"name": "Interest", "score": 0.3447508215904236}, {"name": "Joy", "score": 0.04089464992284775}, {"name": "Love", "score": 0.0494278147816658}, {"name": "Nostalgia", "score": 0.05771852657198906}, {"name": "Pain", "score": 0.08658157289028168}, {"name": "Pride", "score": 0.028028974309563637}, {"name": "Realization", "score": 0.21145027875900269}, {"name": "Relief", "score": 0.033535465598106384}, {"name": "Romance", "score": 0.03916332498192787}, {"name": "Sadness", "score": 0.20380182564258575}, {"name": "Satisfaction", "score": 0.05481785535812378}, {"name": "Shame", "score": 0.07316616177558899}, {"name": "Surprise (negative)", "score": 0.10167598724365234}, {"name": "Surprise (positive)", "score": 0.07470414787530899}, {"name": "Sympathy", "score": 0.06435695290565491}, {"name": "Tiredness", "score": 0.16774457693099976}, {"name": "Triumph", "score": 0.013636237010359764}], "facs": null, "descriptions": null}]}]}}}], "errors": []}}]