[{"source": {"type": "file", "filename": "captured_image.jpg", "content_type": "image/jpeg", "md5sum": "18e321f8e035ce1f911f7e88c481b728"}, "results": {"predictions": [{"file": "captured_image.jpg", "file_type": "image", "models": {"face": {"metadata": null, "grouped_predictions": [{"id": "face_0", "predictions": [{"frame": 0, "time": 0.0, "prob": 0.9999819993972778, "box": {"x": 363.764892578125, "y": 153.83383178710938, "w": 172.9368896484375, "h": 238.2864990234375}, "emotions": [{"name": "Admiration", "score": 0.06257153302431107}, {"name": "Adoration", "score": 0.048325881361961365}, {"name": "Aesthetic Appreciation", "score": 0.04667166993021965}, {"name": "Amusement", "score": 0.07606004178524017}, {"name": "Anger", "score": 0.07164327055215836}, {"name": "Anxiety", "score": 0.24429455399513245}, {"name": "Awe", "score": 0.07742906361818314}, {"name": "Awkwardness", "score": 0.1837121844291687}, {"name": "Boredom", "score": 0.7682908177375793}, {"name": "Calmness", "score": 0.3142387568950653}, {"name": "Concentration", "score": 0.40491536259651184}, {"name": "Confusion", "score": 0.358205646276474}, {"name": "Contemplation", "score": 0.2588597238063812}, {"name": "Contempt", "score": 0.12613685429096222}, {"name": "Contentment", "score": 0.07647652924060822}, {"name": "Craving", "score": 0.04174437373876572}, {"name": "Desire", "score": 0.033007342368364334}, {"name": "Determination", "score": 0.09739713370800018}, {"name": "Disappointment", "score": 0.4311591684818268}, {"name": "Disgust", "score": 0.07468191534280777}, {"name": "Distress", "score": 0.3124908208847046}, {"name": "Doubt", "score": 0.3299529552459717}, {"name": "Ecstasy", "score": 0.01935930922627449}, {"name": "Embarrassment", "score": 0.15090849995613098}, {"name": "Empathic Pain", "score": 0.1216420978307724}, {"name": "Entrancement", "score": 0.10478965193033218}, {"name": "Envy", "score": 0.04049668088555336}, {"name": "Excitement", "score": 0.032817572355270386}, {"name": "Fear", "score": 0.12903694808483124}, {"name": "Guilt", "score": 0.13769279420375824}, {"name": "Horror", "score": 0.05325466766953468}, {"name": "Interest", "score": 0.19605562090873718}, {"name": "Joy", "score": 0.040620360523462296}, {"name": "Love", "score": 0.054398294538259506}, {"name": "Nostalgia", "score": 0.07259788364171982}, {"name": "Pain", "score": 0.1752801090478897}, {"name": "Pride", "score": 0.039368461817502975}, {"name": "Realization", "score": 0.15087245404720306}, {"name": "Relief", "score": 0.04473551735281944}, {"name": "Romance", "score": 0.03303029015660286}, {"name": "Sadness", "score": 0.4566449820995331}, {"name": "Satisfaction", "score": 0.05834035575389862}, {"name": "Shame", "score": 0.1343458741903305}, {"name": "Surprise (negative)", "score": 0.058468297123909}, {"name": "Surprise (positive)", "score": 0.035996876657009125}, {"name": "Sympathy", "score": 0.07247796654701233}, {"name": "Tiredness", "score": 0.4115571975708008}, {"name": "Triumph", "score": 0.016740277409553528}], "facs": null, "descriptions": null}]}, {"id": "face_1", "predictions": [{"frame": 0, "time": 0.0, "prob": 0.9994766116142273, "box": {"x": 319.41412353515625, "y": 307.79412841796875, "w": 28.349090576171875, "h": 58.450439453125}, "emotions": [{"name": "Admiration", "score": 0.1026650220155716}, {"name": "Adoration", "score": 0.10607689619064331}, {"name": "Aesthetic Appreciation", "score": 0.057545844465494156}, {"name": "Amusement", "score": 0.2251311093568802}, {"name": "Anger", "score": 0.0851672887802124}, {"name": "Anxiety", "score": 0.1954691857099533}, {"name": "Awe", "score": 0.09475112706422806}, {"name": "Awkwardness", "score": 0.1786961406469345}, {"name": "Boredom", "score": 0.23041203618049622}, {"name": "Calmness", "score": 0.26411205530166626}, {"name": "Concentration", "score": 0.2883218824863434}, {"name": "Confusion", "score": 0.2977701723575592}, {"name": "Contemplation", "score": 0.1790800839662552}, {"name": "Contempt", "score": 0.11252281069755554}, {"name": "Contentment", "score": 0.14198528230190277}, {"name": "Craving", "score": 0.0450504906475544}, {"name": "Desire", "score": 0.06083304062485695}, {"name": "Determination", "score": 0.09046141058206558}, {"name": "Disappointment", "score": 0.33399495482444763}, {"name": "Disgust", "score": 0.09795483201742172}, {"name": "Distress", "score": 0.3134811222553253}, {"name": "Doubt", "score": 0.22960367798805237}, {"name": "Ecstasy", "score": 0.0659644827246666}, {"name": "Embarrassment", "score": 0.15324848890304565}, {"name": "Empathic Pain", "score": 0.13463915884494781}, {"name": "Entrancement", "score": 0.09400137513875961}, {"name": "Envy", "score": 0.03395998477935791}, {"name": "Excitement", "score": 0.13125404715538025}, {"name": "Fear", "score": 0.13302534818649292}, {"name": "Guilt", "score": 0.12556256353855133}, {"name": "Horror", "score": 0.0689413771033287}, {"name": "Interest", "score": 0.22487668693065643}, {"name": "Joy", "score": 0.20342473685741425}, {"name": "Love", "score": 0.17041289806365967}, {"name": "Nostalgia", "score": 0.07723762094974518}, {"name": "Pain", "score": 0.2919466197490692}, {"name": "Pride", "score": 0.07453381270170212}, {"name": "Realization", "score": 0.16900478303432465}, {"name": "Relief", "score": 0.1143956258893013}, {"name": "Romance", "score": 0.061460379511117935}, {"name": "Sadness", "score": 0.34783878922462463}, {"name": "Satisfaction", "score": 0.17973555624485016}, {"name": "Shame", "score": 0.11808186769485474}, {"name": "Surprise (negative)", "score": 0.06594464927911758}, {"name": "Surprise (positive)", "score": 0.053860586136579514}, {"name": "Sympathy", "score": 0.0708218663930893}, {"name": "Tiredness", "score": 0.2536082863807678}, {"name": "Triumph", "score": 0.05049720034003258}], "facs": null, "descriptions": null}]}, {"id": "face_2", "predictions": [{"frame": 0, "time": 0.0, "prob": 0.9999790191650391, "box": {"x": 190.28623962402344, "y": 344.5040588378906, "w": 24.450164794921875, "h": 35.886993408203125}, "emotions": [{"name": "Admiration", "score": 0.10597473382949829}, {"name": "Adoration", "score": 0.1342102587223053}, {"name": "Aesthetic Appreciation", "score": 0.05586733669042587}, {"name": "Amusement", "score": 0.3110300898551941}, {"name": "Anger", "score": 0.06875935196876526}, {"name": "Anxiety", "score": 0.1444496214389801}, {"name": "Awe", "score": 0.08272494375705719}, {"name": "Awkwardness", "score": 0.17139731347560883}, {"name": "Boredom", "score": 0.17235848307609558}, {"name": "Calmness", "score": 0.22821146249771118}, {"name": "Concentration", "score": 0.1810094714164734}, {"name": "Confusion", "score": 0.1948224902153015}, {"name": "Contemplation", "score": 0.10636067390441895}, {"name": "Contempt", "score": 0.09645574539899826}, {"name": "Contentment", "score": 0.16305260360240936}, {"name": "Craving", "score": 0.0475284680724144}, {"name": "Desire", "score": 0.06919409334659576}, {"name": "Determination", "score": 0.06588854640722275}, {"name": "Disappointment", "score": 0.26551032066345215}, {"name": "Disgust", "score": 0.10349224507808685}, {"name": "Distress", "score": 0.26956743001937866}, {"name": "Doubt", "score": 0.14863429963588715}, {"name": "Ecstasy", "score": 0.09288173168897629}, {"name": "Embarrassment", "score": 0.1567619889974594}, {"name": "Empathic Pain", "score": 0.15365588665008545}, {"name": "Entrancement", "score": 0.08426840603351593}, {"name": "Envy", "score": 0.031128641217947006}, {"name": "Excitement", "score": 0.18037743866443634}, {"name": "Fear", "score": 0.1301823854446411}, {"name": "Guilt", "score": 0.11197980493307114}, {"name": "Horror", "score": 0.06970526278018951}, {"name": "Interest", "score": 0.21244052052497864}, {"name": "Joy", "score": 0.2957906424999237}, {"name": "Love", "score": 0.2482910305261612}, {"name": "Nostalgia", "score": 0.08546078205108643}, {"name": "Pain", "score": 0.3988417088985443}, {"name": "Pride", "score": 0.0759863406419754}, {"name": "Realization", "score": 0.12811370193958282}, {"name": "Relief", "score": 0.10128633677959442}, {"name": "Romance", "score": 0.07487506419420242}, {"name": "Sadness", "score": 0.4392813444137573}, {"name": "Satisfaction", "score": 0.2251323163509369}, {"name": "Shame", "score": 0.11803457140922546}, {"name": "Surprise (negative)", "score": 0.051952578127384186}, {"name": "Surprise (positive)", "score": 0.04471759870648384}, {"name": "Sympathy", "score": 0.07658763229846954}, {"name": "Tiredness", "score": 0.20128178596496582}, {"name": "Triumph", "score": 0.05956851318478584}], "facs": null, "descriptions": null}]}]}}}], "errors": []}}]